MANIFEST.in
README.md
setup.py
micros1client/__init__.py
micros1client/cli_parser.py
micros1client/client.py
micros1client.egg-info/PKG-INFO
micros1client.egg-info/SOURCES.txt
micros1client.egg-info/dependency_links.txt
micros1client.egg-info/entry_points.txt
micros1client.egg-info/not-zip-safe
micros1client.egg-info/requires.txt
micros1client.egg-info/top_level.txt
micros1client/configs/__init__.py
micros1client/configs/config_cli.py
micros1client/configs/config_handler.py
micros1client/tests/__init__.py
micros1client/tests/base_tests.py