Metadata-Version: 1.0
Name: micros1client
Version: 1.5
Summary: python and cli Client for providing  access to micros1 microservice after authtication from tokenleader
Home-page: https://github.com/microservice-tsp-billing/micros1-client
Author: Bhujay Kumar Bhatta
Author-email: bhujay.bhatta@yahoo.com
License: Apache Software License
Platform: UNKNOWN
